gradema/__init__.py
gradema/grader/__init__.py
gradema/grader/_grader.py
gradema/grader/_reporter.py
gradema/grader/console/__init__.py
gradema/grader/console/_console.py
gradema/grader/console/_indent.py
gradema/grader/console/_runner.py
gradema/grader/console/_util.py
gradema/py.typed
gradema/section/__init__.py
gradema/section/_section.py
gradema/test/__init__.py
gradema/test/_command.py
gradema/test/_dummy.py
gradema/test/_exists.py
gradema/test/_python.py
gradema/test/_reporter.py
gradema/test/_rust.py
gradema/test/_stdio.py
gradema/test/_test.py
gradema/test/argument.py
gradema-0.1.1.dist-info/LICENSE
gradema-0.1.1.dist-info/METADATA
gradema-0.1.1.dist-info/WHEEL
gradema-0.1.1.dist-info/RECORD
