Metadata-Version: 2.1
Name: gradema
Version: 0.1.1
Summary: The utility you need to easily configure auto-grading
Home-page: https://gradema.readthedocs.io
License: MIT
Author: Lavender Shannon
Author-email: retrodaredevil@gmail.com
Requires-Python: >=3.10,<4.0
Classifier: License :: OSI Approved :: MIT License
Classifier: Programming Language :: Python :: 3
Classifier: Programming Language :: Python :: 3.10
Classifier: Programming Language :: Python :: 3.11
Classifier: Programming Language :: Python :: 3.12
Requires-Dist: editorconfig (>=0.12.4,<0.13.0)
Requires-Dist: python-magic (>=0.4.27,<0.5.0)
Requires-Dist: rich (==13.7.1)
Project-URL: Repository, https://gitlab.com/classroomcode/gradema/gradema
